multiremote_fm.py
multiremote_fm-0.1.dist-info/LICENSE
multiremote_fm-0.1.dist-info/METADATA
multiremote_fm-0.1.dist-info/WHEEL
multiremote_fm-0.1.dist-info/top_level.txt
multiremote_fm-0.1.dist-info/RECORD
